phpipam_mcp_server/__init__.py
phpipam_mcp_server/server.py
phpipam_mcp_server-0.2.1.dist-info/LICENSE
phpipam_mcp_server-0.2.1.dist-info/METADATA
phpipam_mcp_server-0.2.1.dist-info/WHEEL
phpipam_mcp_server-0.2.1.dist-info/entry_points.txt
phpipam_mcp_server-0.2.1.dist-info/top_level.txt
phpipam_mcp_server-0.2.1.dist-info/RECORD
