Metadata-Version: 2.1
Name: phpipam-mcp-server
Version: 0.2.1
Summary: MCP server for phpIPAM IP address management and network infrastructure
Author-email: Rory McMahon <rory.mcmahon@vocus.com.au>
License: MIT
Project-URL: Homepage, https://github.com/InfraMCP/phpipam-mcp-server
Project-URL: Repository, https://github.com/InfraMCP/phpipam-mcp-server
Project-URL: Issues, https://github.com/InfraMCP/phpipam-mcp-server/issues
Project-URL: Documentation, https://github.com/InfraMCP/phpipam-mcp-server#readme
Keywords: mcp,phpipam,ipam,network,ip-management
Classifier: Development Status :: 3 - Alpha
Classifier: Intended Audience :: Developers
Classifier: License :: OSI Approved :: MIT License
Classifier: Programming Language :: Python :: 3
Classifier: Programming Language :: Python :: 3.8
Classifier: Programming Language :: Python :: 3.9
Classifier: Programming Language :: Python :: 3.10
Classifier: Programming Language :: Python :: 3.11
Classifier: Programming Language :: Python :: 3.12
Requires-Python: >=3.8
License-File: LICENSE
Requires-Dist: mcp==1.14.1
Requires-Dist: requests==2.32.5
Provides-Extra: dev
Requires-Dist: pytest==8.3.3; extra == "dev"
Requires-Dist: pytest-asyncio==0.24.0; extra == "dev"
Requires-Dist: black==24.8.0; extra == "dev"
Requires-Dist: isort==5.13.2; extra == "dev"
Requires-Dist: mypy>=1.0.0; extra == "dev"
Requires-Dist: build>=0.10.0; extra == "dev"
Requires-Dist: twine>=4.0.0; extra == "dev"
Requires-Dist: pylint>=3.0.0; extra == "dev"
Provides-Extra: security
Requires-Dist: safety>=3.0.0; extra == "security"
Requires-Dist: pip-audit>=2.6.0; extra == "security"
